{"device_id":"6e44d895-416a-4d9a-b582-e12da6ae6ea9","app_id":"com.runtastic.android.results.lite","activity_kind":"event","app_version":"4.13","city":"Dortmund","country":"de","country_subdivision":"North Rhine-Westphalia","device_id_android":"6e44d895-416a-4d9a-b582-e12da6ae6ea9","device_id_fingerprint":"f8b5cefe8a936834813edb241afeb73a","device_name":"CLT-L29","device_type":"phone","language":"de","network":"Organic","os_name":"android","tmstamp":1586533684,"timezone":"UTC+0200","utm_source":"google-play","utm_medium":"organic","usage_interaction_name":"click.workout","usage_interaction_type":"workout_tab","user_agent":"Dalvik/2.1.0 (Linux; U; Android 9; CLT-L29 Build/HUAWEICLT-L29)","event_name":"UsageInteraction","id":"8d6325ab-8d51-4b85-a6d2-6066075dfac7"}